vaultapi/__init__.py
vaultapi/api.py
vaultapi/auth.py
vaultapi/database.py
vaultapi/exceptions.py
vaultapi/ipaddress.py
vaultapi/models.py
vaultapi/payload.py
vaultapi/rate_limit.py
vaultapi/routes.py
vaultapi/server.py
vaultapi/transit.py
vaultapi/util.py
vaultapi/version.py
vaultapi-0.3.4.dist-info/licenses/LICENSE
vaultapi-0.3.4.dist-info/METADATA
vaultapi-0.3.4.dist-info/WHEEL
vaultapi-0.3.4.dist-info/entry_points.txt
vaultapi-0.3.4.dist-info/top_level.txt
vaultapi-0.3.4.dist-info/RECORD
