Metadata-Version: 2.4
Name: VaultAPI
Version: 0.3.4
Summary: Lightweight API to store/retrieve secrets to/from an encrypted Database
Author-email: Vignesh Rao <svignesh1793@gmail.com>
License: MIT License
Project-URL: Homepage, https://github.com/thevickypedia/VaultAPI
Project-URL: Docs, https://thevickypedia.github.io/VaultAPI
Project-URL: Source, https://github.com/thevickypedia/VaultAPI
Project-URL: Bug Tracker, https://github.com/thevickypedia/VaultAPI/issues
Project-URL: Release Notes, https://github.com/thevickypedia/VaultAPI/blob/main/release_notes.rst
Keywords: vaultapi,vault,fastapi,sqlite3,fernet
Classifier: License :: OSI Approved :: MIT License
Classifier: Programming Language :: Python :: 3.10
Classifier: Programming Language :: Python :: 3.11
Classifier: Development Status :: 5 - Production/Stable
Classifier: Operating System :: MacOS :: MacOS X
Classifier: Operating System :: Microsoft :: Windows
Classifier: Operating System :: POSIX :: Linux
Requires-Python: >=3.10
License-File: LICENSE
Requires-Dist: click==8.1.*
Requires-Dist: cryptography==44.0.*
Requires-Dist: fastapi==0.115.*
Requires-Dist: pydantic==2.10.*
Requires-Dist: pydantic-settings==2.7.*
Requires-Dist: python-dotenv==1.0.*
Requires-Dist: PyYAML==6.0.*
Requires-Dist: requests==2.32.*
Requires-Dist: uvicorn==0.34.*
Provides-Extra: dev
Requires-Dist: sphinx==5.1.1; extra == "dev"
Requires-Dist: pre-commit; extra == "dev"
Requires-Dist: recommonmark; extra == "dev"
Requires-Dist: gitverse; extra == "dev"
Dynamic: license-file
